pyimapsync/__init__.py
pyimapsync/__main__.py
pyimapsync/_version.py
pyimapsync/shared.py
pyimapsync-0.0.2.dist-info/LICENSE
pyimapsync-0.0.2.dist-info/METADATA
pyimapsync-0.0.2.dist-info/WHEEL
pyimapsync-0.0.2.dist-info/entry_points.txt
pyimapsync-0.0.2.dist-info/top_level.txt
pyimapsync-0.0.2.dist-info/RECORD
